openfinops/__init__.py
openfinops/cli.py
openfinops/cli/database.py
openfinops/config/__init__.py
openfinops/config/local_config.py
openfinops/dashboard/__init__.py
openfinops/dashboard/auth_middleware.py
openfinops/dashboard/cfo_dashboard.py
openfinops/dashboard/coo_dashboard.py
openfinops/dashboard/dashboard_router.py
openfinops/dashboard/finance_analyst_dashboard.py
openfinops/dashboard/iam_cli.py
openfinops/dashboard/iam_config.yaml
openfinops/dashboard/iam_config_loader.py
openfinops/dashboard/iam_system.py
openfinops/dashboard/infrastructure_leader_dashboard.py
openfinops/dashboard/model_cost_dashboard.py
openfinops/dashboard/recommendations_dashboard.py
openfinops/database/__init__.py
openfinops/database/database_manager.py
openfinops/iac/__init__.py
openfinops/iac/client.py
openfinops/iac/provider.py
openfinops/iac/resources.py
openfinops/iac/terraform_generator.py
openfinops/insights/__init__.py
openfinops/insights/delivery.py
openfinops/insights/insight_engine.py
openfinops/insights/personas/__init__.py
openfinops/insights/personas/business_lead.py
openfinops/insights/personas/cfo.py
openfinops/insights/personas/engineer.py
openfinops/insights/personas/finance.py
openfinops/ml/__init__.py
openfinops/ml/anomaly_detector.py
openfinops/ml/cost_predictor.py
openfinops/ml/pattern_recognition.py
openfinops/multicloud/__init__.py
openfinops/multicloud/cloud_provider.py
openfinops/multicloud/cost_comparator.py
openfinops/multicloud/optimizer.py
openfinops/observability/__init__.py
openfinops/observability/ai_recommendations.py
openfinops/observability/alerting_engine.py
openfinops/observability/cost_configuration.py
openfinops/observability/cost_observatory.py
openfinops/observability/cost_reporting.py
openfinops/observability/distributed_telemetry.py
openfinops/observability/finops_dashboards.py
openfinops/observability/hardware_recommendations.py
openfinops/observability/infrastructure_automation.py
openfinops/observability/infrastructure_dashboard.py
openfinops-0.3.0.dist-info/licenses/LICENSE
openfinops-0.3.0.dist-info/METADATA
openfinops-0.3.0.dist-info/WHEEL
openfinops-0.3.0.dist-info/entry_points.txt
openfinops-0.3.0.dist-info/top_level.txt
openfinops-0.3.0.dist-info/RECORD
