Metadata-Version: 2.4
Name: openfinops
Version: 0.3.0
Summary: Open Source FinOps Platform for AI/ML Cost Observability with Intelligent LLM-Powered Recommendations
Author-email: OpenFinOps Contributors <durai@infinidatum.net>
Maintainer-email: OpenFinOps Contributors <durai@infinidatum.net>
License: Apache-2.0
Project-URL: Homepage, https://github.com/openfinops/openfinops
Project-URL: Documentation, https://openfinops.readthedocs.io/
Project-URL: Repository, https://github.com/openfinops/openfinops
Project-URL: Bug Tracker, https://github.com/openfinops/openfinops/issues
Keywords: finops,cost-optimization,observability,ai-ml,cloud-cost,aws,azure,gcp,openai,anthropic,llm-monitoring,rag-monitoring,cost-attribution,visualization,dashboard,telemetry,multi-cloud,intelligent-recommendations,hardware-optimization,gpu-optimization,scaling-recommendations,auto-scaling,llm-powered,claude
Classifier: Development Status :: 3 - Alpha
Classifier: Intended Audience :: Developers
Classifier: Intended Audience :: System Administrators
Classifier: Intended Audience :: Financial and Insurance Industry
Classifier: Topic :: System :: Monitoring
Classifier: Topic :: Office/Business :: Financial
Classifier: Topic :: Scientific/Engineering :: Visualization
Classifier: License :: OSI Approved :: Apache Software License
Classifier: Programming Language :: Python :: 3
Classifier: Programming Language :: Python :: 3.8
Classifier: Programming Language :: Python :: 3.9
Classifier: Programming Language :: Python :: 3.10
Classifier: Programming Language :: Python :: 3.11
Classifier: Programming Language :: Python :: 3.12
Classifier: Operating System :: OS Independent
Requires-Python: >=3.8
License-File: LICENSE
Requires-Dist: numpy>=1.24.0
Requires-Dist: matplotlib>=3.7.0
Requires-Dist: tornado>=6.0.0
Requires-Dist: flask>=2.0.0
Requires-Dist: flask-socketio>=5.3.0
Requires-Dist: flask-cors>=4.0.0
Requires-Dist: eventlet>=0.33.0
Requires-Dist: requests>=2.28.0
Requires-Dist: pyyaml>=6.0
Provides-Extra: aws
Requires-Dist: boto3>=1.26.0; extra == "aws"
Provides-Extra: azure
Requires-Dist: azure-monitor-query>=1.1.0; extra == "azure"
Requires-Dist: azure-identity>=1.12.0; extra == "azure"
Provides-Extra: gcp
Requires-Dist: google-cloud-monitoring>=2.11.0; extra == "gcp"
Provides-Extra: openai
Requires-Dist: openai>=1.0.0; extra == "openai"
Provides-Extra: anthropic
Requires-Dist: anthropic>=0.8.0; extra == "anthropic"
Provides-Extra: postgres
Requires-Dist: psycopg2-binary>=2.9.0; extra == "postgres"
Provides-Extra: mongodb
Requires-Dist: pymongo>=4.3.0; extra == "mongodb"
Provides-Extra: dev
Requires-Dist: pytest>=7.0.0; extra == "dev"
Requires-Dist: pytest-cov>=4.0.0; extra == "dev"
Requires-Dist: black>=23.0.0; extra == "dev"
Requires-Dist: ruff>=0.1.0; extra == "dev"
Requires-Dist: mypy>=1.0.0; extra == "dev"
Provides-Extra: all
Requires-Dist: boto3>=1.26.0; extra == "all"
Requires-Dist: azure-monitor-query>=1.1.0; extra == "all"
Requires-Dist: azure-identity>=1.12.0; extra == "all"
Requires-Dist: google-cloud-monitoring>=2.11.0; extra == "all"
Requires-Dist: openai>=1.0.0; extra == "all"
Requires-Dist: anthropic>=0.8.0; extra == "all"
Requires-Dist: psycopg2-binary>=2.9.0; extra == "all"
Requires-Dist: pymongo>=4.3.0; extra == "all"
Dynamic: license-file
